sciaiot/__init__.py
sciaiot/py.typed
sciaiot/airflow/__init__.py
sciaiot/airflow/providers/__init__.py
sciaiot/airflow/providers/tdengine/__init__.py
sciaiot/airflow/providers/tdengine/hooks/__init__.py
sciaiot/airflow/providers/tdengine/hooks/tdengine.py
sciaiot/airflow/providers/tdengine/operators/__init__.py
sciaiot/airflow/providers/tdengine/operators/tdengine.py
apache_airflow_providers_tdengine-0.1.1.dist-info/LICENSE
apache_airflow_providers_tdengine-0.1.1.dist-info/METADATA
apache_airflow_providers_tdengine-0.1.1.dist-info/WHEEL
apache_airflow_providers_tdengine-0.1.1.dist-info/entry_points.txt
apache_airflow_providers_tdengine-0.1.1.dist-info/top_level.txt
apache_airflow_providers_tdengine-0.1.1.dist-info/RECORD
