Metadata-Version: 2.1
Name: apache-airflow-providers-tdengine
Version: 0.1.1
Summary: The Apache Airflow provider package for TDengine built by SCIA IoT.
Author-email: Nick Yao <ipaddicting@gmail.com>
License: Apache License 2.0
Project-URL: Homepage, https://github.com/scia-iot
Project-URL: Source, https://github.com/scia-iot/airflow-providers-tdengine/
Classifier: Framework :: Apache Airflow
Classifier: Framework :: Apache Airflow :: Provider
Requires-Python: ~=3.12
License-File: LICENSE
Requires-Dist: apache-airflow>=2.9.2
Requires-Dist: taospy>=2.7.13
